symchaos/__init__.py
symchaos/runall
symchaos/symchaos.f90
symchaos/symchaos.py
symchaos/ini/all_palettes.ini
symchaos/ini/clifford.ini
symchaos/ini/example.ini
symchaos/ini/fern.ini
symchaos/ini/hopalong1.ini
symchaos/ini/hopalong2.ini
symchaos/ini/mondrian.ini
symchaos/ini/no_f90.ini
symchaos/ini/quilt.ini
symchaos/ini/quilt1.ini
symchaos/ini/quilt2.ini
symchaos/ini/quilt3.ini
symchaos/ini/rot4.ini
symchaos/ini/rot7.ini
symchaos/ini/rot9.ini
symchaos/ini/test.ini
symchaos/ini/triangle.ini
symchaos/ini/vary_cyclic.ini
symchaos/ini/vary_neighborhood.ini
symchaos/ini/vary_random.ini
symchaos/ini/vary_random_walk.ini
symchaos-0.9.0.dist-info/LICENSE
symchaos-0.9.0.dist-info/METADATA
symchaos-0.9.0.dist-info/WHEEL
symchaos-0.9.0.dist-info/top_level.txt
symchaos-0.9.0.dist-info/RECORD
