Metadata-Version: 2.1
Name: symchaos
Version: 0.9.0
Summary: Symmetric Chaos
Home-page: https://gitlab.com/RolfSander/symchaos
Author: Rolf Sander
Author-email: mail@rolf-sander.net
License: UNKNOWN
Platform: UNKNOWN
Classifier: Programming Language :: Python :: 3.6
Classifier: License :: OSI Approved :: GNU General Public License (GPL)
Classifier: Operating System :: OS Independent
Classifier: Natural Language :: English
Classifier: Topic :: Multimedia :: Graphics
Requires-Python: >=3.6
Requires-Dist: configparser
Requires-Dist: datetime
Requires-Dist: matplotlib
Requires-Dist: numpy
